Workbook

Sheet Инструкция
A1: Excel-калькулятор цен сети «Зеленое Яблоко»
A3: Назначение: управление ценой, маржой и валовой прибылью по топовым позициям, сравнение с рынком и сценарное моделирование.
A5: Как пользоваться:
A6: 1. На листе «Исходные данные» находятся товары, штрихкоды, закупочная и розничная цена ЗЯ, цены конкурентов.
A7: Данные загружаются из исходного файла или дополняются вручную.
A8: 2. На листе «Продажи» вручную заполняются текущие продажи в Зеленом Яблоке по штрихкоду: количество, выручка, валовая прибыль.
A9: 3. Лист «Расчеты» автоматически формирует аналитику по ценам, марже, валовой прибыли и всем сценариям.
A10: 4. Лист «Dashboard» отображает KPI, количество позиций выше/ниже рынка, суммарную текущую и прогнозную валовую прибыль.
A11: 5. Лист «Сценарный анализ» содержит сводный анализ по всем позициям и сценариям, а также рекомендации.
A13: Поля ручного ввода:
A14: - Лист «Исходные данные»: все ценовые поля (если их нужно скорректировать), штрихкоды и наименование.
A15: - Лист «Продажи»: Количество_продаж, Выручка, Валовая_прибыль по каждому штрихкоду.
... A22: Важно: не изменяйте формулы в расчётных столбцах. Добавляйте новые позиции через вставку строк внутрь таблиц.

Sheet Исходные данные
A1: Наименование | B1: Штрихкод | C1: Закупочная_цена_ЗЯ | D1: Розничная_цена_ЗЯ | E1: Цена_7_Континент | F1: Цена_Европейский | G1: Цена_Тропики | H1: Цена_Мята | I1: Цена_Отличный | J1: Цена_Оптовик_Молоток | K1: Цена_Оптовик_Редукторный
A2: Белизна гипохлорид 1л | B2: 4665272570017 | C2: 29 | D2: 39 | F2: 55 | I2: 52 | J2: 41
A3: Гель белизна Санфор 3в1 700мл | B3: 4602984001637 | C3: 87.83 | D3: 119 (159) | H3: 131 | J3: 110
A4: Гель Ласка 1л для Черного Эффект восстановления | B4: 9000101409321 | C4: 236.18 | D4: 339 | F4: 349 | H4: 301 | J4: 265
A5: Кондиционер ABC для белья 1440мл Элегантная Орхидея | B5: 8690511000983 | C5: 235 | D5: 289 | F5: 285 | H5: 288 | J5: 240 | K5: 230
A6: Порошок ABC авт 3кг Лимон | B6: 8690511171614 | C6: 255 | D6: 385 | F6: 356 | H6: 394 | I6: 329 | K6: 299
A7: Порошок Ариэль авт 3кг Колор | B7: 5413149333437 | C7: 496.63 | D7: 599 | E7: 673 | H7: 540 | J7: 490
A8: Отбеливатель Бос плюс Макс 500г | B8: 4600905000332 | C8: 127 | D8: 179 | I8: 191
A9: Средство AOS для посуды 450г Лимон | B9: 4604049012305 | C9: 67.94 | D9: 85 | E9: 107 | H9: 85 | I9: 88 | J9: 80 | K9: 71
A10: Средство AOS для посуды 900г Лимон | B10: 4604049095476 | C10: 131.78 | D10: 199 | H10: 169 | I10: 179 | J10: 140 | K10: 138
A11: Средство Грасс Azelit Антижир для кухни спрей 600мл | B11: 4607072197537 | C11: 116.07 | D11: 159 | E11: 157 | H11: 157 | J11: 125
A12: Средство Доместос 1,5л Ультра блеск | B12: 8714100797525 | C12: 160.16 | D12: 249
A13: Средство Доместос 500мл Ультра блеск | B13: 8714100707890 | C13: 77.02 | D13: 139 | H13: 124 | J13: 105
A14: Кассеты для бритья Жиллетт Фьюжн 4шт | B14: 7702018874460
A15: Зубная паста Сплат Профессионал 100г Отбеливание плюс | B15: 4603014023704
A16: Мыло жидкое Грасс Milana 1000мл Perfume | B16: 4670113604165
A17: Салфетки влажные Мануоки детские 80шт | B17: 4620174812764
A18: Полотенца бумажные Папия Декор 3 слоя 2 рулона | B18: 4604857001782 | C18: 99.19 | D18: 129 (145) | F18: 134 | H18: 127 | I18: 139 | J18: 100
A19: Туалетная бумага Папия 3сл 4рул белая | B19: 8690536023936
A20: Полотенца бумажные Zemma 2сл 2рул | B20: 4670199857349 | C20: 77 | D20: 99 (125)
A21: Туалетная бумага Zemma Плюс 2сл 4шт Белая | B21: 4605331003308 | C21: 77 | D21: 99 (125) | H21: 95 | J21: 90
A23: Крупа Гречневая (ядрица) Первый сорт 1кг | B23: 2057030071836 | C23: 48 | D23: 59 | E23: 75 | I23: 61 | J23: 60
A24: Крупа Рисовая (рис шлифованный) 1кг | B24: 2058077055810 | C24: 60 | D24: 79 | E24: 87 | I24: 91 | J24: 80 | K24: 80
A25: Крупа Увелка Гречневая Экстра 800г | B25: 4607016240893 | C25: 71.35 | D25: 89 | E25: 99 | F25: 94 | G25: 100 | H25: 89 | I25: 91 | J25: 90
A26: Мак изд Барилла №5 Спагетти 450г | B26: 8076809576093 | C26: 81.79 | D26: 119 | E26: 95 | F26: 100 | G26: 135 | H26: 94 | I26: 96 | J26: 105 | K26: 92
A27: Мак изд Барилла №98 Фузилли 450г | B27: 8076809576000 | C27: 81.79 | D27: 119 | E27: 108 | F27: 109 | G27: 115 | H27: 122 | I27: 199 | J27: 105 | K27: 92
A28: Мак изд Макфа Спагетти 400г | B28: 4601780010508 | C28: 49.51 | D28: 65 | E28: 68 | F28: 64 | H28: 77 | I28: 61 | J28: 80 | K28: 57
A29: Мак изд Макфа Спирали 400г | B29: 4601780006990 | C29: 49.51 | D29: 65 | E29: 68 | F29: 64 | G29: 68 | H29: 63 | I29: 62 | J29: 62 | K29: 56
A30: Мука Макфа в/с 2кг | B30: 4601780002565 | C30: 93 | D30: 119 | E30: 139 | F30: 107 | G30: 140 | H30: 157 | I30: 108 | J30: 130
A31: Мука Снежана в/с 2кг | B31: 1905000299036 | C31: 83.16 | D31: 99 (115) | G31: 110 | H31: 116 | I31: 108 | J31: 90
A32: Рис Агроальянс для плова 900г | B32: 4607072711535 | C32: 116.5 | D32: 135 (175) | F32: 202 | I32: 197 | J32: 145
A33: Рис Дарман шлифованный Премиум 2кг | B33: 4607157483784 | C33: 240 | D33: 299 | F33: 310 | I33: 293 | J33: 265
A34: Рис Дарман шлифованный Экстра 800г | B34: 4607157483029 | C34: 91.5 | D34: 115 | E34: 113 | F34: 123 | G34: 120 | J34: 110
A35: Рис Тамаша MIAD Индия мешочек 1кг | B35: 8906010700720 | C35: 165 | D35: 249 | E35: 250 | G35: 245 | H35: 244 | I35: 238 | J35: 230
A36: Сахар песок 1кг | B36: 2067468029354 | C36: 58.9 | D36: 65 | E36: 60 | F36: 64 | G36: 85 | I36: 78 | J36: 80
A37: Сода пищевая 500г | B37: 4640001890031 | C37: 38.16 | D37: 55 | E37: 55 | F37: 56 | G37: 55 | H37: 52 | I37: 53 | J37: 50
A38: Соль поваренная пищевая Помол №1 1кг Руссоль | B38: 4610007350228 | C38: 9.32 | D38: 17 | E38: 28 | F38: 22 | G38: 20 | H38: 19 | I38: 21 | J38: 18 | K38: 16
A39: Соль Экстра йодированная 500г | B39: 4607005090126 | C39: 65.38 | D39: 85 | F39: 84 | I39: 81 | J39: 55
A41: Пюре Агуша фруктовое пауч 160г Яблоко банан клубн земляника злаки | B41: 4690228110771 | C41: 63.16 | D41: 79 (135) | H41: 76 | I41: 80 | J41: 75
A42: Пюре ФрутоНяня 90г Яблоко натур. 4 мес д/пак | B42: 4600338006130 | C42: 47.48 | D42: 59 (95) | J42: 45
A43: Смесь Малютка 2 600г | B43: 4600209011133 | C43: 577.03 | D43: 689 | H43: 699 | I43: 732 | J43: 660
A44: Смесь Нутрилон 2 Премиум 600г с 6-мес молочн Нутриция | B44: 4600209011256 | C44: 828.52 | D44: 955 | G44: 1095 | I44: 979 | J44: 935 | K44: 915
A46: Хлебцы Др Корнер Рисовые с молочным шоколадом 67г | B46: 4607065716301 | C46: 96.62 | D46: 125 | E46: 130 | F46: 85 | H46: 119 | J46: 120
A47: Хлебцы Др Корнер Рисовые с темным шоколадом 67г | B47: 4607065716288 | C47: 96.62 | D47: 125 | E47: 130 | F47: 85 | H47: 119 | J47: 120
A49: Батончик Сникерс 50,5г | B49: 4607065001445 | C49: 42.9 | D49: 55 (89) | E49: 55 | F49: 54 | G49: 70 | H49: 59 | I49: 51 | J49: 50 | K49: 48
A50: Драже M&M's 45г с арахисом | B50: 4607065000790 | C50: 65.88 | D50: 85 (99) | E50: 80 | F50: 87 | G50: 85 | H50: 73 | I50: 72 | J50: 60 | K50: 59
A51: Киндер Буэно Т30 Ферреро 43г | B51: 80052760 | C51: 90.08 | D51: 109 (139) | E51: 116 | F51: 106 | G51: 135 | I51: 129 | K51: 80
A52: Конфеты Баунти Минис | B52: 2164599 | C52: 700 | D52: 899 (990) | E52: 935 | F52: 934 | G52: 1100 | H52: 925 | I52: 839 | J52: 815
A53: Конфеты Мерси 250г Ассорти | B53: 4014400901191 | C53: 370.3 | D53: 479 | E53: 450 | F53: 431 | G53: 455 | J53: 400
A54: Конфеты Нива К/О | B54: 2174260 | C54: 314.26 | D54: 430 | E54: 443 | F54: 402 | G54: 380 | I54: 376
A55: Конфеты Птица Дивная суфле в шоколаде | B55: 2126719 | C55: 617.97 | D55: 740 | E55: 689 | F55: 574 | G55: 780 | I55: 699 | J55: 650
A56: Конфеты Сникерс Минис | B56: 2176475 | C56: 700 | D56: 899 (980) | E56: 935 | F56: 934 | G56: 1043 | H56: 925 | I56: 852 | J56: 815
A57: Конфеты Тоффифе шоколадные 125г | B57: 4014400400007 | C57: 173.68 | D57: 209 (225) | E57: 182 | F57: 190 | H57: 160 | I57: 199 | K57: 152
A58: Печенье Кофе джой кофейное 78г | B58: 8996001301760 | C58: 88.82 | D58: 99 | F58: 111 | G58: 155 | I58: 95 | J58: 78
A59: Печенье Милка Чоко Бисквит 150г | B59: 7622300590970 | C59: 190 | D59: 249 | E59: 238 | F59: 243 | H59: 233
A60: Пирожное Медвежонок Барни 150г с молочной начинкой | B60: 4600375914399 | C60: 107.43 | D60: 169 | F60: 132 | G60: 160 | H60: 145 | I60: 127 | J60: 125
A61: Шоколад Киндер Т4 50г | B61: 80177609 | C61: 117 | D61: 139 | E61: 148 | G61: 145 | H61: 106 | J61: 90 | K61: 85
A62: Шоколад Милка молочный 80г | B62: 7622202048326 | C62: 108.85 | D62: 139 | F62: 157 | G62: 150 | H62: 134 | K62: 111
A63: Шоколадная паста Нутелла ст/б 350г | B63: 8000500004388 | C63: 380 | D63: 499 | E63: 693 | F63: 693 | G63: 540 | H63: 474 | I63: 665 | K63: 304
A65: Какао порошок Золотой ярлык 100г К/О | B65: 4600300000739 | C65: 91.65 | D65: 125 | G65: 145 | H65: 135 | I65: 134
A66: Кофе Бушидо Оригинал ст/б 100г | B66: 7610121710318 | C66: 648.19 | D66: 899 | E66: 895 | F66: 925 | G66: 895 | H66: 890 | I66: 924
A67: Кофе Мехмет Эфенди молотый по турецки банка 250г | B67: 8690627023401 | C67: 487.2 | D67: 649 | E67: 668 | F67: 548 | G67: 570 | H67: 581 | J67: 480
A68: Чай Джамал черный Эрл Грей 450г | B68: 4796003453955 | C68: 590 | D68: 759 | E68: 720 | F68: 752 | G68: 755 | H68: 750 | I68: 684 | K68: 667
A69: Чай Джамбо черный отборн кр/л 250г | B69: 4791038627272 | C69: 350 | D69: 439 | E69: 530 | F69: 320 | G69: 415 | H69: 400 | I69: 384 | J69: 370
A70: Чай Ричард Лорд Грей черный 180г | B70: 4660115901317 | C70: 219.83 | D70: 299 | E70: 259 | F70: 266 | G70: 295 | H70: 296
A72: Горошек Бондюэль зеленый ж/б 425мл | B72: 3083680048774 | C72: 115 | D72: 149 | E72: 138 | F72: 170 | I72: 135
A73: Горошек По-Княжески ж/б 420мл кольцо | B73: 4688355676178 | C73: 65.7 | D73: 89 | E73: 92 | F73: 84 | G73: 90 | H73: 69 | I73: 83 | J73: 80 | K73: 80
A74: Грибы Опята Кормилица маринов ст/б 580мл | B74: 4606530003465 | C74: 201.96 | D74: 239 | E74: 245 | G74: 260 | I74: 229 | J74: 215 | K74: 211
A75: Корнишоны По-Княжески 6-9см 670г евро | B75: 4630017929832 | C75: 123.25 | D75: 149 | E75: 148 | F75: 148 | I75: 145 | J75: 145
A76: Кукуруза Бондюэль ж/б 425мл | B76: 3083680002875 | C76: 115 | D76: 149 | E76: 138 | F76: 170 | I76: 138
A77: Кукуруза Кормилица ж/б 425мл ключ | B77: 4606530004035 | C77: 81 | D77: 99 | E77: 89 | G77: 115 | I77: 99 | J77: 85 | K77: 88
A78: Кукуруза По-Княжески ж/б 425мл | B78: 4688355676017 | C78: 74.8 | D78: 99 | E78: 105 | F78: 100 | H78: 79 | I78: 96 | J78: 90 | K78: 90
A79: Маслины Лорадо черн б/к ж/б 314мл | B79: 4813515009217 | C79: 186.5 | D79: 199 | F79: 234 | G79: 240
A80: Томатная паста Краснодарочка 25% ст/б 510г | B80: 4607025591368 | C80: 132.29 | D80: 165 | E80: 164
A81: Фасоль Бондюэль красная ж/б 425мл | B81: 3083680009508 | C81: 111 | D81: 159 | E81: 148 | G81: 200 | I81: 133
A82: Фасоль Кормилица красная ж/б 425мл | B82: 4606530472865 | C82: 76.5 | D82: 99 | G82: 105 | I82: 86 | J82: 75 | K82: 80
A84: Горчица Махеевъ зернистая ст/б 190г | B84: 4604248012632 | C84: 68 | D84: 85 | E84: 85 | H84: 88 | I84: 84 | J84: 80
A85: Кетчуп Хайнц д/п 320г Томатный | B85: 4601674084714 | C85: 94.58 | D85: 129 | E85: 137 | F85: 139 | G85: 145 | H85: 142
A86: Майонез Слобода провансаль 67% 400мл | B86: 4600699502210 | C86: 103 | D86: 129 | E86: 130 | F86: 103 | H86: 132 | I86: 118 | J86: 115 | K86: 121
A87: Майонез Слобода провансаль 67% 800мл | B87: 4600699505525 | C87: 169 | D87: 199 | E87: 210 | F87: 211 | G87: 225 | H87: 220 | I87: 194 | J87: 180 | K87: 198
A88: Соус Барилла Песто Дженовезе ст/б 190г | B88: 8076809513753 | C88: 253.01 | D88: 329 | E88: 329 | G88: 360 | H88: 343 | I88: 321
A89: Соус Хайнц д/п 200г Кисло сладкий | B89: 4601674086282 | C89: 110.96 | D89: 139 | E89: 137 | F89: 139 | G89: 145 | H89: 142 | I89: 139
A91: Масло оливковое Боргес EV ст/б 0,5л | B91: 8410179100036 | C91: 663 | D91: 795 | E91: 798 | G91: 900 | H91: 779 | I91: 1140
A92: Масло оливковое Хангров EV ст/б 250мл | B92: 4603552022825 | C92: 346.6 | D92: 455 (539) | F92: 480 | H92: 569 | I92: 562
A93: Масло подсолнечное Слобода рафин 1л | B93: 4600699501121 | C93: 146 | D93: 175 | E93: 175 | F93: 188 | G93: 200 | H93: 188 | I93: 176 | J93: 155 | K93: 155
A94: Масло подсолнечное Золотая Семечка 1л | B94: 4680001220025
A95: Масло подсолнечное Светлица 0,9л (либо самое дешевое) | B95: 4607085810782 | C95: 99.9 | D95: 125
A97: Зефир Пастухов Молочный с ванилью в мол бельг шоколаде 60г | B97: 4610050690111 | C97: 142.5 | D97: 175 | F97: 180 | G97: 185 | H97: 184 | I97: 172
A98: Йогурт Актибио питьев 870г Злаки | B98: 4600605032800 | C98: 142.05 | D98: 169 (225) | E98: 198 | F98: 189 | G98: 185 | H98: 182 | I98: 182 | J98: 180 | K98: 183
A99: Йогурт Даниссимо Фантазия 105г хруст шарики | B99: 4600605019351 | C99: 67.2 | D99: 89 | F99: 93 | G99: 90 | I99: 90 | J99: 90 | K99: 87
A100: Йогурт Савушкин TEOS Греческий 2% 250г Натуральный | B100: 4810268031793
A101: Йогурт Савушкин TEOS Греческий 2% 140г Натуральный | B101: 4810268030369
A102: Кефир Дарман 2,5% п/бут 1000г | B102: 4607157481698 | C102: 100 | D102: 125 | F102: 135 | G102: 135 | H102: 135
A103: Кефир Согратль 2,5% 900мл п/пак | B103: 4603731707109 | C103: 98 | D103: 119 | E103: 125 | F103: 126 | I103: 126 | J103: 130 | K103: 129
A104: Кефир Чабан 2,5% п/пак 0,9л | B104: 4607195112721 | C104: 110.17 | D104: 129 | E104: 127 | F104: 130 | G104: 125 | H104: 126 | J104: 115
A105: Масло сливочное Дарман 82,5% 200г | B105: 4607157484965
A106: Масло сливочное Дарман 82,5% 450г | B106: 4607157484972
A107: Масло сливочное Приэльбрусье 82,5% 180г | B107: 4607195112431 | C107: 187.96 | D107: 235 (299) | E107: 235 | F107: 235 | G107: 225 | H107: 218 | J107: 210
A108: Масло сливочное Чабан Халяль 82.5% 330г | B108: 4610092774428 | C108: 377.2 | D108: 455 (615) | E108: 470 | G108: 470 | H108: 437 | J108: 420 | K108: 410
A109: Масло сливочное Чабан Халяль 82.5% 180г | B109: 4607195113018
...

Sheet Продажи
A1: Штрихкод | B1: Количество_продаж | C1: Выручка | D1: Валовая_прибыль

Sheet Расчеты
A1: Наименование | B1: Штрихкод | C1: Закупочная_цена_ЗЯ | D1: Розничная_цена_ЗЯ | E1: Цена_7_Континент | F1: Цена_Европейский | G1: Цена_Тропики | H1: Цена_Мята | I1: Цена_Отличный | J1: Цена_Оптовик_Молоток | K1: Цена_Оптовик_Редукторный | L1: Средняя_цена_рынка | M1: Медианная_цена_рынка | N1: Мин_цена_конкурента | O1: Макс_цена_конкурента | P1: Отклонение_от_средней | Q1: Отклонение_от_медианы | R1: Отклонение_от_минимума | S1: Рейтинг_цены | T1: Текущая_наценка_% | U1: Текущая_маржа_% | V1: Валовая_прибыль_на_ед | W1: Количество_продаж | X1: Текущая_выручка | Y1: Текущая_валовая_прибыль | Z1: Текущая_маржа_общая_% | AA1: Целевая_маржа_сценарий_5 | AB1: Новая_цена_сценарий_1 | AC1: Наценка_сценарий_1 | AD1: Маржа_сценарий_1 | AE1: ВП_ед_сценарий_1 | AF1: Новая_цена_сценарий_2 | AG1: Наценка_сценарий_2 | AH1: Маржа_сценарий_2 | AI1: ВП_ед_сценарий_2 | AJ1: Новая_цена_сценарий_3 | AK1: Наценка_сценарий_3 | AL1: Маржа_сценарий_3 | AM1: ВП_ед_сценарий_3 | AN1: Новая_цена_сценарий_4 | AO1: Наценка_сценарий_4 | AP1: Маржа_сценарий_4 | AQ1: ВП_ед_сценарий_4 | AR1: Новая_цена_сценарий_5 | AS1: Наценка_сценарий_5 | AT1: Маржа_сценарий_5 | AU1: ВП_ед_сценарий_5 | AV1: Прогноз_выручка_1 | AW1: Прогноз_ВП_1 | AX1: Прогноз_выручка_2 | AY1: Прогноз_ВП_2 | AZ1: Прогноз_выручка_3 | BA1: Прогноз_ВП_3 | BB1: Прогноз_выручка_4 | BC1: Прогноз_ВП_4 | BD1: Прогноз_выручка_5 | BE1: Прогноз_ВП_5
A2: =XLOOKUP(B2,Исходные [1]данные!B:B,Исходные [1]данные!A:A,"") -> #NAME? | C2: =XLOOKUP(B2,Исходные [1]данные!B:B,Исходные [1]данные!C:C,"") -> #NAME? | D2: =XLOOKUP(B2,Исходные [1]данные!B:B,Исходные [1]данные!D:D,"") -> #NAME? | E2: =XLOOKUP(B2,Исходные [1]данные!B:B,Исходные [1]данные!E:E,"") -> #NAME? | F2: =XLOOKUP(B2,Исходные [1]данные!B:B,Исходные [1]данные!F:F,"") -> #NAME? | G2: =XLOOKUP(B2,Исходные [1]данные!B:B,Исходные [1]данные!G:G,"") -> #NAME? | H2: =XLOOKUP(B2,Исходные [1]данные!B:B,Исходные [1]данные!H:H,"") -> #NAME? | I2: =XLOOKUP(B2,Исходные [1]данные!B:B,Исходные [1]данные!I:I,"") -> #NAME? | J2: =XLOOKUP(B2,Исходные [1]данные!B:B,Исходные [1]данные!J:J,"") -> #NAME? | K2: =XLOOKUP(B2,Исходные [1]данные!B:B,Исходные [1]данные!K:K,"") -> #NAME? | L2: =IFERROR(AVERAGE(E2:K2),"") | M2: =IFERROR(MEDIAN(E2:K2),"") | N2: =IFERROR(MIN(E2:K2),"") | O2: =IFERROR(MAX(E2:K2),"") | P2: =IF(L2>0,(D2-L2)/L2,"") -> #NAME? | Q2: =IF(M2>0,(D2-M2)/M2,"") -> #NAME? | R2: =IF(N2>0,(D2-N2)/N2,"") -> #NAME? | S2: =IF(D2>0,RANK(D2,E2:K2),"") -> #NAME? | T2: =IF(C2>0,(D2-C2)/C2,"") -> #NAME? | U2: =IF(D2>0,(D2-C2)/D2,"") -> #NAME? | V2: =IF(AND(C2>0,D2>0),D2-C2,"") -> #NAME? | W2: =IFERROR(XLOOKUP(B2,Продажи!A:A,Продажи!B:B,""),"") | X2: =IF(W2>0,W2*D2,"") -> #VALUE! | Y2: =IF(W2>0,W2*V2,"") -> #VALUE! | Z2: =IF(X2>0,Y2/X2,"") -> #VALUE! | AB2: =L2 | AC2: =IF(AND(AB2>0,C2>0),(AB2-C2)/C2,"") -> #NAME? | AD2: =IF(AB2>0,(AB2-C2)/AB2,"") -> #VALUE! | AE2: =IF(AND(AB2>0,C2>0),AB2-C2,"") -> #NAME? | AF2: =M2 | AG2: =IF(AND(AF2>0,C2>0),(AF2-C2)/C2,"") -> #NAME? | AH2: =IF(AF2>0,(AF2-C2)/AF2,"") -> #VALUE! | AI2: =IF(AND(AF2>0,C2>0),AF2-C2,"") -> #NAME? | AJ2: =N2 | AK2: =IF(AND(AJ2>0,C2>0),(AJ2-C2)/C2,"") -> #NAME? | AL2: =IF(AJ2>0,(AJ2-C2)/AJ2,"") -> #VALUE! | AM2: =IF(AND(AJ2>0,C2>0),AJ2-C2,"") -> #NAME? | AO2: =IF(AND(AN2>0,C2>0),(AN2-C2)/C2,"") -> #NAME? | AP2: =IF(AN2>0,(AN2-C2)/AN2,"") | AQ2: =IF(AND(AN2>0,C2>0),AN2-C2,"") -> #NAME? | AR2: =IF(AA2>0,C2/(1-AA2),"") | AS2: =IF(AND(AR2>0,C2>0),(AR2-C2)/C2,"") -> #NAME? | AT2: =AA2 -> 0 | AU2: =IF(AND(AR2>0,C2>0),AR2-C2,"") -> #NAME? | AV2: =IF(W2>0,W2*AB2,"") -> #VALUE! | AW2: =IF(W2>0,W2*AE2,"") -> #VALUE! | AX2: =IF(W2>0,W2*AF2,"") -> #VALUE! | AY2: =IF(W2>0,W2*AI2,"") -> #VALUE! | AZ2: =IF(W2>0,W2*AJ2,"") -> #VALUE! | BA2: =IF(W2>0,W2*AM2,"") -> #VALUE! | BB2: =IF(W2>0,W2*AN2,"") -> #VALUE! | BC2: =IF(W2>0,W2*AQ2,"") -> #VALUE! | BD2: =IF(W2>0,W2*AR2,"") -> #VALUE! | BE2: =IF(W2>0,W2*AU2,"") -> #VALUE!

Sheet Dashboard
A1: KPI
A2: Позиций выше рынка | B2: =COUNTIF(Расчеты!P:P,">0") -> 0
A3: Позиций ниже рынка | B3: =COUNTIF(Расчеты!P:P,"<0") -> 0
A4: Средняя маржа | B4: =AVERAGE(Расчеты!Z:Z) -> #VALUE!
A5: Средняя наценка | B5: =AVERAGE(Расчеты!T:T) -> #NAME?
A6: Суммарная текущая ВП | B6: =SUM(Расчеты!Y:Y) -> #VALUE!
A7: Суммарная прогнозная ВП (сценарий 5) | B7: =SUM(Расчеты!BE:BE) -> #VALUE!

Sheet Сценарный анализ
A1: Сценарий | B1: Суммарная валовая прибыль | C1: Комментарий
A2: Текущая | B2: =SUM(Расчеты!Y:Y) -> #VALUE!
A3: Средняя цена рынка | B3: =SUM(Расчеты!AW:AW) -> #VALUE!
A4: Медианная цена рынка | B4: =SUM(Расчеты!AY:AY) -> #VALUE!
A5: Мин. цена конкурента | B5: =SUM(Расчеты!BA:BA) -> #VALUE!
A6: Произвольная цена | B6: =SUM(Расчеты!BC:BC) -> #VALUE!
A7: Целевая маржа | B7: =SUM(Расчеты!BE:BE) -> #VALUE!
